alib_lib/__init__.py
alib_lib/module1.py
alib_lib/module2.py
alib_lib-0.1.0.dist-info/METADATA
alib_lib-0.1.0.dist-info/WHEEL
alib_lib-0.1.0.dist-info/licenses/LICENSE
alib_lib-0.1.0.dist-info/RECORD
