Metadata-Version: 2.4
Name: alib_lib
Version: 0.1.0
Summary: It is my first time creating a library, I hope it will be helpful for you.
Author-email: Alina <minoriiko@mail.ru>
License-File: LICENSE
Classifier: License :: OSI Approved :: MIT License
Classifier: Operating System :: OS Independent
Classifier: Programming Language :: Python :: 3
Requires-Python: >=3.6
